setup.py
funny_tool/__init__.py
funny_tool/bleach.py
funny_tool/dytt.py
funny_tool/funny_tool.py
funny_tool/tvserials.py
funny_tool.egg-info/PKG-INFO
funny_tool.egg-info/SOURCES.txt
funny_tool.egg-info/dependency_links.txt
funny_tool.egg-info/entry_points.txt
funny_tool.egg-info/not-zip-safe
funny_tool.egg-info/requires.txt
funny_tool.egg-info/top_level.txt
funny_tool/utils/TVList.py
funny_tool/utils/__init__.py
funny_tool/utils/rrys_login.py