Metadata-Version: 1.1
Name: funny-tool
Version: 0.2.8
Summary: The funny tools to download movies and comics
Home-page: https://github.com/CCharlieLi/funny_tool
Author: CCharlieLi
Author-email: ccharlieli@live.com
License: MIT
Download-URL: https://github.com/CCharlieLi/funny_tool/releases
Keywords: download,bleach,dytt
Platform: UNKNOWN
Classifier: Development Status :: 4 - Beta
Classifier: Environment :: Console
Classifier: Intended Audience :: End Users/Desktop
Classifier: License :: OSI Approved :: MIT License
Classifier: Programming Language :: Python :: 3
Classifier: Operating System :: MacOS :: MacOS X
Classifier: Operating System :: Microsoft :: Windows
Classifier: Operating System :: POSIX
Classifier: Programming Language :: Python
Classifier: Natural Language :: English
Classifier: Natural Language :: Chinese (Simplified)
